{
  "video_id": "noNwCNNIxm4",
  "total": 18,
  "comments": [
    {
      "comment_id": "UgzTPHuhotJGQ4h0CXt4AaABAg",
      "video_id": "noNwCNNIxm4",
      "video_title": "Gorakhpur News | गोरखपुर में बदला लेने के लिए हुई थी भाजपा नेता की हत्या, CCTV से पकड़े गए हत्यारे",
      "channel": "Amrit Vichar",
      "video_date": null,
      "author": "@SurendarTiwari-l6n",
      "author_channel": "UCOyOxIKhI-4mFaBC5qQgQOA",
      "text_raw": "नेता जी भी गुंडा थे।।चेहरा किसी रावण से कम नहीं दिखता।।चेहरे से ही दबंगई झलक रही ऐसे में कोई शरीफ इन्हें ऊपर भेजा।।",
      "like_count": "19",
      "reply_count": "1",
      "published_at": "2026-04-12T11:22:16.757340+00:00",
      "time_relative": "1 month ago",
      "is_reply": false,
      "parent_id": null,
      "language": "",
      "content_hash": "4b20a4417ecaec6359427fbb02ac3e3fe6f9c0721e2ccc7b7a04b0fba77d0ac4",
      "scraped_at": "2026-05-12T11:22:17.459478+00:00"
    },
    {
      "comment_id": "UgxI46uXlUEnEY3I9Ap4AaABAg",
      "video_id": "noNwCNNIxm4",
      "video_title": "Gorakhpur News | गोरखपुर में बदला लेने के लिए हुई थी भाजपा नेता की हत्या, CCTV से पकड़े गए हत्यारे",
      "channel": "Amrit Vichar",
      "video_date": null,
      "author": "@yogendrayadav939",
      "author_channel": "UCrhyFhrlIrOG481_PG3ql3Q",
      "text_raw": "Desh me sabse bande harami to neta or police wale hi hai",
      "like_count": "3",
      "reply_count": "1",
      "published_at": "2026-04-12T11:22:16.758532+00:00",
      "time_relative": "1 month ago",
      "is_reply": false,
      "parent_id": null,
      "language": "",
      "content_hash": "768f568340345f9981de3347e49b1d65e78481ed19f8a620b6efad2303d94564",
      "scraped_at": "2026-05-12T11:22:17.459509+00:00"
    },
    {
      "comment_id": "UgxU0mnlHAPpHo1-CTt4AaABAg",
      "video_id": "noNwCNNIxm4",
      "video_title": "Gorakhpur News | गोरखपुर में बदला लेने के लिए हुई थी भाजपा नेता की हत्या, CCTV से पकड़े गए हत्यारे",
      "channel": "Amrit Vichar",
      "video_date": null,
      "author": "@SurendraSharma-",
      "author_channel": "UCaHJQP_ut2X8wkyFwjQ7sNw",
      "text_raw": "देश के हर नेता के बच्चे और उनके चमचो का गुंडागिरिब्जय ही होती है",
      "like_count": "3",
      "reply_count": 0,
      "published_at": "2026-04-12T11:22:16.759499+00:00",
      "time_relative": "1 month ago",
      "is_reply": false,
      "parent_id": null,
      "language": "",
      "content_hash": "6ba19191972cbb3319c8c7f27243d20189282767a57669e2856526d40b9c7c94",
      "scraped_at": "2026-05-12T11:22:17.459531+00:00"
    },
    {
      "comment_id": "UgwVscRKkLl6jeCo-594AaABAg",
      "video_id": "noNwCNNIxm4",
      "video_title": "Gorakhpur News | गोरखपुर में बदला लेने के लिए हुई थी भाजपा नेता की हत्या, CCTV से पकड़े गए हत्यारे",
      "channel": "Amrit Vichar",
      "video_date": null,
      "author": "@gopalkrishangaur3069",
      "author_channel": "UCWj4BTaXk73bH8-grdHAnAw",
      "text_raw": "गोरखपुर पुलिस को बहुत बहुत बधाइयां ।\n       🌺🌿🇮🇳 जै हिंद जै भारत ।",
      "like_count": "0",
      "reply_count": 0,
      "published_at": "2026-04-12T11:22:16.760432+00:00",
      "time_relative": "1 month ago",
      "is_reply": false,
      "parent_id": null,
      "language": "",
      "content_hash": "e3ba806407094aacd9a190a30e72e02524a1b34dc6fb9c7fe7c037d8c64d3af3",
      "scraped_at": "2026-05-12T11:22:17.459551+00:00"
    },
    {
      "comment_id": "UgyVkCMUCU55FVINo3d4AaABAg",
      "video_id": "noNwCNNIxm4",
      "video_title": "Gorakhpur News | गोरखपुर में बदला लेने के लिए हुई थी भाजपा नेता की हत्या, CCTV से पकड़े गए हत्यारे",
      "channel": "Amrit Vichar",
      "video_date": null,
      "author": "@MurtjaAli-z1u6s",
      "author_channel": "UCmGca30d-FYYTLdT9XgdFIg",
      "text_raw": "Gundagrdi krwa rha tha",
      "like_count": "1",
      "reply_count": 0,
      "published_at": "2026-04-12T11:22:16.761436+00:00",
      "time_relative": "1 month ago",
      "is_reply": false,
      "parent_id": null,
      "language": "",
      "content_hash": "aa416fd38e4fcbf74d46a0b7ac3cf5930daa7703ebe50c1ec43d0a08e3c3aec0",
      "scraped_at": "2026-05-12T11:22:17.459568+00:00"
    },
    {
      "comment_id": "UgwWJrp8gw0fjFI-VdB4AaABAg",
      "video_id": "noNwCNNIxm4",
      "video_title": "Gorakhpur News | गोरखपुर में बदला लेने के लिए हुई थी भाजपा नेता की हत्या, CCTV से पकड़े गए हत्यारे",
      "channel": "Amrit Vichar",
      "video_date": null,
      "author": "@JesJes-b5y",
      "author_channel": "UC4Ht62adkhaLDbQ_kGSI_fw",
      "text_raw": "Very gud",
      "like_count": "1",
      "reply_count": 0,
      "published_at": "2026-04-12T11:22:16.762467+00:00",
      "time_relative": "1 month ago",
      "is_reply": false,
      "parent_id": null,
      "language": "",
      "content_hash": "75c66fdccafea407f6fafbaa0f5f793b93a1594be947f6e4ce967fb00c5e9329",
      "scraped_at": "2026-05-12T11:22:17.459586+00:00"
    },
    {
      "comment_id": "UgzP4Jw5Ix3evfwzPVt4AaABAg",
      "video_id": "noNwCNNIxm4",
      "video_title": "Gorakhpur News | गोरखपुर में बदला लेने के लिए हुई थी भाजपा नेता की हत्या, CCTV से पकड़े गए हत्यारे",
      "channel": "Amrit Vichar",
      "video_date": null,
      "author": "@agastya_4448",
      "author_channel": "UCSoOZDtjv4lnu1Fqnt4ijwA",
      "text_raw": "Iska matlab murder kar doge",
      "like_count": "0",
      "reply_count": 0,
      "published_at": "2026-04-12T11:22:16.763329+00:00",
      "time_relative": "1 month ago",
      "is_reply": false,
      "parent_id": null,
      "language": "",
      "content_hash": "dcbf55ddf7fe47bcac8fb109950db90e6f70d835843ce5f19adaa295be61cc10",
      "scraped_at": "2026-05-12T11:22:17.459603+00:00"
    },
    {
      "comment_id": "Ugxs4TdjUdyRzqzZ1yx4AaABAg",
      "video_id": "noNwCNNIxm4",
      "video_title": "Gorakhpur News | गोरखपुर में बदला लेने के लिए हुई थी भाजपा नेता की हत्या, CCTV से पकड़े गए हत्यारे",
      "channel": "Amrit Vichar",
      "video_date": null,
      "author": "@shyamchauhan7589",
      "author_channel": "UCb1BSEQTo4ZPOgO_3ncFwKg",
      "text_raw": "Aab kish chij ki suraksha diya ja raha h police ki taraph se😮😮",
      "like_count": "0",
      "reply_count": 0,
      "published_at": "2026-04-12T11:22:16.764543+00:00",
      "time_relative": "1 month ago",
      "is_reply": false,
      "parent_id": null,
      "language": "",
      "content_hash": "36d3410a2021652b263916463984eb5a8dada39b6ffbb76d3ef7b2ec9a74b1db",
      "scraped_at": "2026-05-12T11:22:17.459621+00:00"
    },
    {
      "comment_id": "UgwqypFIudur_z3P7414AaABAg",
      "video_id": "noNwCNNIxm4",
      "video_title": "Gorakhpur News | गोरखपुर में बदला लेने के लिए हुई थी भाजपा नेता की हत्या, CCTV से पकड़े गए हत्यारे",
      "channel": "Amrit Vichar",
      "video_date": null,
      "author": "@virendravikramsingh9813",
      "author_channel": "UCsKxxnKPCP4phNzA7uOPOdg",
      "text_raw": "चेहरे से बहुत सरीफ हैं नेता जी",
      "like_count": "1",
      "reply_count": 0,
      "published_at": "2026-04-12T11:22:16.765616+00:00",
      "time_relative": "1 month ago",
      "is_reply": false,
      "parent_id": null,
      "language": "",
      "content_hash": "d2530504a98e80dc2414e8e3d9923dd1ebd061808493b93587cdc313a4161cfe",
      "scraped_at": "2026-05-12T11:22:17.459639+00:00"
    },
    {
      "comment_id": "UgwKtN2j4oYIm8nq3Vd4AaABAg",
      "video_id": "noNwCNNIxm4",
      "video_title": "Gorakhpur News | गोरखपुर में बदला लेने के लिए हुई थी भाजपा नेता की हत्या, CCTV से पकड़े गए हत्यारे",
      "channel": "Amrit Vichar",
      "video_date": null,
      "author": "@India-c3o",
      "author_channel": "UCysXgDIwZM3eJILE9VhLl2w",
      "text_raw": "आरोपियो का एनकाउंटर क्यूँ नहीं हुआ",
      "like_count": "0",
      "reply_count": 0,
      "published_at": "2026-04-12T11:22:16.766584+00:00",
      "time_relative": "1 month ago",
      "is_reply": false,
      "parent_id": null,
      "language": "",
      "content_hash": "4fb6cd0b86374f566dc3476bfe7b88c02eacfe59c1d2e53cd71d035fca25cc62",
      "scraped_at": "2026-05-12T11:22:17.459657+00:00"
    },
    {
      "comment_id": "UgwCs5bcpXFy9WKZ-fh4AaABAg",
      "video_id": "noNwCNNIxm4",
      "video_title": "Gorakhpur News | गोरखपुर में बदला लेने के लिए हुई थी भाजपा नेता की हत्या, CCTV से पकड़े गए हत्यारे",
      "channel": "Amrit Vichar",
      "video_date": null,
      "author": "@SingeRMantUMissilE121",
      "author_channel": "UCbxegI0tFkMtACCFQjFUmAA",
      "text_raw": "Sarkar Se Hi donon Hath jodkar nivedan hai ki isko jald hi jald encounter kiya jaaye ine Logon Ko",
      "like_count": "0",
      "reply_count": 0,
      "published_at": "2026-04-12T11:22:16.767528+00:00",
      "time_relative": "1 month ago",
      "is_reply": false,
      "parent_id": null,
      "language": "",
      "content_hash": "dbcee55d4bb8d26cdb912ff3eed1fe7c1879db16544029fb18365d1042758921",
      "scraped_at": "2026-05-12T11:22:17.459675+00:00"
    },
    {
      "comment_id": "Ugyq3-ya4yVWvS4fAPd4AaABAg",
      "video_id": "noNwCNNIxm4",
      "video_title": "Gorakhpur News | गोरखपुर में बदला लेने के लिए हुई थी भाजपा नेता की हत्या, CCTV से पकड़े गए हत्यारे",
      "channel": "Amrit Vichar",
      "video_date": null,
      "author": "@Saurabh-w5x",
      "author_channel": "UCfbNGf2ov6G_Jvm30wcdXWw",
      "text_raw": "Ye dono ka encounter kyu nhi hua",
      "like_count": "1",
      "reply_count": 0,
      "published_at": "2026-04-12T11:22:16.768427+00:00",
      "time_relative": "1 month ago",
      "is_reply": false,
      "parent_id": null,
      "language": "",
      "content_hash": "58deb1a59828e6310da6dfc193411edc2dafb0ee37259abb14229af149774116",
      "scraped_at": "2026-05-12T11:22:17.459691+00:00"
    },
    {
      "comment_id": "UgwzKGOKfMlXI8UCtVB4AaABAg",
      "video_id": "noNwCNNIxm4",
      "video_title": "Gorakhpur News | गोरखपुर में बदला लेने के लिए हुई थी भाजपा नेता की हत्या, CCTV से पकड़े गए हत्यारे",
      "channel": "Amrit Vichar",
      "video_date": null,
      "author": "@jaihindNishad-fl3wt",
      "author_channel": "UC8-tcEbG9D6LD3RYKRN-jQQ",
      "text_raw": "Jay nishad raj💪💪💪",
      "like_count": "1",
      "reply_count": 0,
      "published_at": "2026-04-12T11:22:16.769287+00:00",
      "time_relative": "1 month ago",
      "is_reply": false,
      "parent_id": null,
      "language": "",
      "content_hash": "88363d99b6e62a25ef03224d6eb83debd2dfb91bd50511c8efd1f2946ab9e2e8",
      "scraped_at": "2026-05-12T11:22:17.459708+00:00"
    },
    {
      "comment_id": "UgxvmGWPFeHDEx2KRGR4AaABAg",
      "video_id": "noNwCNNIxm4",
      "video_title": "Gorakhpur News | गोरखपुर में बदला लेने के लिए हुई थी भाजपा नेता की हत्या, CCTV से पकड़े गए हत्यारे",
      "channel": "Amrit Vichar",
      "video_date": null,
      "author": "@Awesh.funny.786",
      "author_channel": "UCobzb4VXvM_eGgDP_Gxsj2Q",
      "text_raw": "Agar dam hai chako to\nIncounter karo",
      "like_count": "1",
      "reply_count": 0,
      "published_at": "2026-04-12T11:22:16.770098+00:00",
      "time_relative": "1 month ago",
      "is_reply": false,
      "parent_id": null,
      "language": "",
      "content_hash": "b46401676a0248007ce6346d9d456de84f541775773f54958a95994759c47b4c",
      "scraped_at": "2026-05-12T11:22:17.459727+00:00"
    },
    {
      "comment_id": "UgyOmaBvAR-QzOF3ogF4AaABAg",
      "video_id": "noNwCNNIxm4",
      "video_title": "Gorakhpur News | गोरखपुर में बदला लेने के लिए हुई थी भाजपा नेता की हत्या, CCTV से पकड़े गए हत्यारे",
      "channel": "Amrit Vichar",
      "video_date": null,
      "author": "@DilipkumarLThakkar",
      "author_channel": "UCfRaX-0cMawfhQRBsBPD41A",
      "text_raw": "Bakvas Kar Raha Hai Yeh Sochi Samji Sajish Hai",
      "like_count": "2",
      "reply_count": 0,
      "published_at": "2026-04-12T11:22:16.770954+00:00",
      "time_relative": "1 month ago",
      "is_reply": false,
      "parent_id": null,
      "language": "",
      "content_hash": "0a45ff3aed745aa251506f6d6031c8d6ebd921f1d1730773e209a4bc143a9607",
      "scraped_at": "2026-05-12T11:22:17.459746+00:00"
    },
    {
      "comment_id": "UgwktcPj_moC3xRyeCp4AaABAg",
      "video_id": "noNwCNNIxm4",
      "video_title": "Gorakhpur News | गोरखपुर में बदला लेने के लिए हुई थी भाजपा नेता की हत्या, CCTV से पकड़े गए हत्यारे",
      "channel": "Amrit Vichar",
      "video_date": null,
      "author": "@pcyadav6914",
      "author_channel": "UCKxMu39GYAE9vYvF9inPSLQ",
      "text_raw": "A̤i̤s̤a̤ n̤e̤ b̤h̤i̤ t̤o̤ m̤ṳr̤d̤a̤r̤ l̤i̤y̤a̤ h̤a̤i̤",
      "like_count": "1",
      "reply_count": 0,
      "published_at": "2026-04-12T11:22:16.772014+00:00",
      "time_relative": "1 month ago",
      "is_reply": false,
      "parent_id": null,
      "language": "",
      "content_hash": "9810bbf9795703ef0d512961f8e54e0accc530e26e7bec635e00c4fd16fb785a",
      "scraped_at": "2026-05-12T11:22:17.459761+00:00"
    },
    {
      "comment_id": "UgzTPHuhotJGQ4h0CXt4AaABAg.AUVCYKJ7ZLXAUVHf6hajdq",
      "video_id": "noNwCNNIxm4",
      "video_title": "Gorakhpur News | गोरखपुर में बदला लेने के लिए हुई थी भाजपा नेता की हत्या, CCTV से पकड़े गए हत्यारे",
      "channel": "Amrit Vichar",
      "video_date": null,
      "author": "@ArunKumar-o9z7o",
      "author_channel": "UCJlHrcLdKaUkmP5PSGlSWkA",
      "text_raw": "नेता जी मेरे साथ पढ़े थे इनके पिता सुर्ती बेचते थे इनकी 4 बहन थी ये घर के अकेले थे गरीबी तंगी के वजह से इनकी पढ़ाई छूट गई ये राज गिर मिस्त्री के साथ काम करने लगे पहली बार ये जेल गये थे फीरौती मांगने के जुर्म मे 2004 या 2005 मे उसके बाद होली के टाइम मे इनके ऊपर जान लेवा हमला हुआ दारू के बोतल तोड़ के इनको मारा गया था ये बच गये थे हम ज्यादा नहीं बोलेंगे आप लोग खुद समझदार है जिस इंसान की तंगी गरीबी मे पढ़ाई छूट गई उस इंसान ने इतने कम उम्र मे इतने बड़े मोकाम कैसे हासिल की बिना सरकारी नौकरी के और हा ना मै नेता जी के जात हु ना मै इनके गांव का हूँ और ना इनकी तरक्की से मुझे कोई परेशानी है बट एक बात सत्य है बबुल का पेड़ जो लगाएगा उसको कांटा ही मिलेगा आम नहीं",
      "like_count": "2",
      "reply_count": 0,
      "published_at": "2026-04-12T11:22:17.062437+00:00",
      "time_relative": "1 month ago",
      "is_reply": true,
      "parent_id": null,
      "language": "",
      "content_hash": "1578c1fd73c5486443987487dc903b800aac1749cab9da3533afa5cdd307568f",
      "scraped_at": "2026-05-12T11:22:17.459792+00:00"
    },
    {
      "comment_id": "UgxI46uXlUEnEY3I9Ap4AaABAg.AUV9HBnmSGdAUZpVvdk3Qg",
      "video_id": "noNwCNNIxm4",
      "video_title": "Gorakhpur News | गोरखपुर में बदला लेने के लिए हुई थी भाजपा नेता की हत्या, CCTV से पकड़े गए हत्यारे",
      "channel": "Amrit Vichar",
      "video_date": null,
      "author": "@ABHISHEKSINGH90907",
      "author_channel": "UCKNd7DOVAt-p2DK-aP-0Vaw",
      "text_raw": "Chlo kise ne shi bola",
      "like_count": "0",
      "reply_count": 0,
      "published_at": "2026-04-12T11:22:17.355489+00:00",
      "time_relative": "1 month ago",
      "is_reply": true,
      "parent_id": null,
      "language": "",
      "content_hash": "3656162b7788a9015e159fcd868b2597ebd400703a712792391a97847305807d",
      "scraped_at": "2026-05-12T11:22:17.459803+00:00"
    }
  ]
}